thonnycontrib/data_visualization/__init__.py
thonnycontrib/data_visualization/graphical_view.py
thonnycontrib/data_visualization/hierarchical_view.py
thonnycontrib/data_visualization/locals_variables_view.py
thonnycontrib/data_visualization/representation_format.py
thonnycontrib/data_visualization/sender.py
thonnycontrib/data_visualization/Graphical/DB.py
thonnycontrib/data_visualization/Graphical/graphic.py
thonny_data_visualization-2.0.0.dist-info/LICENSE
thonny_data_visualization-2.0.0.dist-info/METADATA
thonny_data_visualization-2.0.0.dist-info/WHEEL
thonny_data_visualization-2.0.0.dist-info/top_level.txt
thonny_data_visualization-2.0.0.dist-info/RECORD
