Metadata-Version: 2.1
Name: thonny-data_visualization
Version: 2.0.0
Summary: A Thonny plug-in to visualize your data
Home-page: https://github.com/etrubbers/thonny-data_visualization
Author: ['Jean de Briey', 'Etienne Rubbers']
Author-email: ['jean.debriey@student.uclouvain.be', 'etienne.rubbers@student.uclouvain.be']
License: UCLouvain
Keywords: Thonny,data visualization
Classifier: Intended Audience :: Developers
Classifier: License :: OSI Approved :: MIT License
Classifier: Programming Language :: Python :: 3
Requires-Python: >=3.7
License-File: LICENSE
Requires-Dist: thonny >=4.1.4
Requires-Dist: networkx
